.gitignore
.travis.yml
CHANGELOG.md
CONTRIBUTING.md
COPYING
Dockerfile-debian
Dockerfile-redhat
README.md
Singularity
docker-compose.yml
formatters.py
niceman.cfg
readthedocs.yml
requirements-devel.txt
requirements.txt
setup.cfg
setup.py
setup_support.py
tox.ini
docs/Makefile
docs/source/acknowledgements.rst
docs/source/background.rst
docs/source/cmdline.rst
docs/source/conf.py
docs/source/glossary.rst
docs/source/index.rst
docs/source/modref.rst
docs/source/related.rst
docs/source/_static/niceman_logo.png
docs/source/_templates/autosummary/module.rst
docs/source/sandbox/ReproNim Entities.png
docs/source/sandbox/ReproNim Entities.xml
docs/source/sandbox/hierarchy.rst
docs/source/sandbox/packages.rst
docs/source/usecases/index.rst
niceman/__init__.py
niceman/api.py
niceman/base.py
niceman/cmd.py
niceman/config.py
niceman/conftest.py
niceman/consts.py
niceman/dochelpers.py
niceman/log.py
niceman/utils.py
niceman/version.py
niceman.egg-info/PKG-INFO
niceman.egg-info/SOURCES.txt
niceman.egg-info/dependency_links.txt
niceman.egg-info/entry_points.txt
niceman.egg-info/requires.txt
niceman.egg-info/top_level.txt
niceman/cmdline/__init__.py
niceman/cmdline/common_args.py
niceman/cmdline/helpers.py
niceman/cmdline/main.py
niceman/cmdline/tests/__init__.py
niceman/cmdline/tests/test_helpers.py
niceman/distributions/__init__.py
niceman/distributions/base.py
niceman/distributions/conda.py
niceman/distributions/debian.py
niceman/distributions/docker.py
niceman/distributions/neurodebian.py
niceman/distributions/piputils.py
niceman/distributions/redhat.py
niceman/distributions/singularity.py
niceman/distributions/vcs.py
niceman/distributions/venv.py
niceman/distributions/tests/__init__.py
niceman/distributions/tests/test_conda.py
niceman/distributions/tests/test_debian.py
niceman/distributions/tests/test_distribution.py
niceman/distributions/tests/test_docker.py
niceman/distributions/tests/test_environment.py
niceman/distributions/tests/test_piputils.py
niceman/distributions/tests/test_redhat.py
niceman/distributions/tests/test_singularity.py
niceman/distributions/tests/test_vcs.py
niceman/distributions/tests/test_venv.py
