Metadata-Version: 1.0
Name: niceman
Version: 0.1.0
Summary: Neuroimaging Computational Environments Manager
Home-page: UNKNOWN
Author: The NICEMAN Team and Contributors
Author-email: team@niceman.org
License: UNKNOWN
Platform: UNKNOWN
